evenfasterapi/__init__.py
evenfasterapi/core.py
evenfasterapi-0.1.21.dist-info/METADATA
evenfasterapi-0.1.21.dist-info/WHEEL
evenfasterapi-0.1.21.dist-info/RECORD
