Metadata-Version: 2.3
Name: evenfasterapi
Version: 0.1.21
Summary: 
License: MIT
Author: Miles Copeland Luce
Requires-Python: >=3.13,<4.0
Classifier: License :: OSI Approved :: MIT License
Classifier: Programming Language :: Python :: 3
Classifier: Programming Language :: Python :: 3.13
Requires-Dist: fastapi (>=0.116.1,<0.117.0)
Requires-Dist: loguru (>=0.7.3,<0.8.0)
